setup.py
rstsandbox/__init__.py
rstsandbox.egg-info/PKG-INFO
rstsandbox.egg-info/SOURCES.txt
rstsandbox.egg-info/dependency_links.txt
rstsandbox.egg-info/requires.txt
rstsandbox.egg-info/top_level.txt
rstsandbox/amarsi/AdaptiveComponentStatus_pb2.py
rstsandbox/amarsi/__init__.py
rstsandbox/cbse/ComponentInfo_pb2.py
rstsandbox/cbse/ComponentState_pb2.py
rstsandbox/cbse/InputPort_pb2.py
rstsandbox/cbse/OutputPort_pb2.py
rstsandbox/cbse/Tick_pb2.py
rstsandbox/cbse/__init__.py
rstsandbox/cogimon/ModelComponentConfig_pb2.py
rstsandbox/cogimon/__init__.py
rstsandbox/communicationpatterns/ResourceAllocation_pb2.py
rstsandbox/communicationpatterns/__init__.py
rstsandbox/devices/__init__.py
rstsandbox/devices/flexirob/RobotStateCollection_pb2.py
rstsandbox/devices/flexirob/RobotState_pb2.py
rstsandbox/devices/flexirob/__init__.py
rstsandbox/hri/Head_pb2.py
rstsandbox/hri/PersonHypotheses_pb2.py
rstsandbox/hri/PersonHypothesis_pb2.py
rstsandbox/hri/__init__.py
rstsandbox/kinematics/JointJerksCollection_pb2.py
rstsandbox/kinematics/JointJerks_pb2.py
rstsandbox/kinematics/__init__.py
rstsandbox/monitoring/ProcessAnomalyCollection_pb2.py
rstsandbox/monitoring/ProcessAnomaly_pb2.py
rstsandbox/monitoring/ProcessCuesCollection_pb2.py
rstsandbox/monitoring/ProcessCues_pb2.py
rstsandbox/monitoring/__init__.py
rstsandbox/robot/ForceApplication_pb2.py
rstsandbox/robot/JointStateCollection_pb2.py
rstsandbox/robot/JointState_pb2.py
rstsandbox/robot/WeightsCollection_pb2.py
rstsandbox/robot/Weights_pb2.py
rstsandbox/robot/__init__.py
rstsandbox/signalprocessing/InstantaneousPhase_pb2.py
rstsandbox/signalprocessing/__init__.py
rstsandbox/vision/EncodedImageCollection_pb2.py
rstsandbox/vision/EncodedImage_pb2.py
rstsandbox/vision/HeadObject_pb2.py
rstsandbox/vision/HeadObjects_pb2.py
rstsandbox/vision/__init__.py