Metadata-Version: 1.0
Name: rstsandbox
Version: 0.16.7
Summary: Robotics Systems Types - Sandbox
Home-page: https://code.cor-lab.org/projects/rst
Author: Johannes Wienke
Author-email: jwienke@techfak.uni-bielefeld.de
License: GPLv3
Platform: UNKNOWN
